{
    "exhibitions": [
        {
            "id": "polenovo2016-2017",
            "name": "Художественные династии России",
            "description": "Семья Художников Ростемберских - Пилипенко",
            "from": "28 декабря 2016",
            "to": "15 января 2017",
            "address": "Государственный Мемориальный Историко-Художественный и Природный Музей-Заповедник Б.Д.Поленова",
            "artists": "Пилипенко Михаил, Пилипенко Виктория, Пилипенко Сергей, Ростемберская Галина",
            "materials": "Живопись (холст масло), эмаль, скульптура (дерево), батик (роспись по шелку)",
            "photos": [
                {
                    "src": "/i/enamel.jpg",
                    "alt": "test",
                    "title": "Зима холст/масло"
                },
                {
                    "src": "/i/sculpt.jpg",
                    "alt": "Пилипенко Сергей, Художественная обработка дерева",
                    "title": "Музыкант - скульптура дерево/краситель"
                },
                {
                    "src": "/i/paint.jpg",
                    "alt": "test",
                    "title": "test"
                },
                {
                    "src": "/i/batik.jpg",
                    "alt": "Пилипенко Виктория, батик, роспись по шелку",
                    "title": "Жаворонок"
                }
            ]
        }
    ]
}